pysqlparse/__init__.py
pysqlparse/parser.py
tests/__init__.py
tests/test_parser.py
pysqlparse-0.0.2.dist-info/LICENSE
pysqlparse-0.0.2.dist-info/METADATA
pysqlparse-0.0.2.dist-info/WHEEL
pysqlparse-0.0.2.dist-info/top_level.txt
pysqlparse-0.0.2.dist-info/RECORD
